<?xml version="1.0"?>
<deformerWeight>
  <headerInfo fileName="C:/Users/sakri/Downloads/UNIVERSITY/2nd Year Game DEV/Game Production Big Team Project/Curio.Co/Curio_Co/Maya Models/Character Assets/EnemyModels/neck joint.xml" worldMatrix="2.188879 0.000000 0.000000 0.000000 0.000000 0.123988 0.028307 0.000000 0.000000 -0.430267 1.884593 0.000000 -0.024595 10.727999 -0.107124 1.000000 "/>
  <shape name="Neck_JointShape" group="0" stride="3" size="871" max="870">
    <point index="0" value=" 0.604191 4.080044 -1.050457"/>
    <point index="1" value=" 0.230780 4.080044 -1.284731"/>
    <point index="2" value=" -0.230781 4.080044 -1.284731"/>
    <point index="3" value=" -0.604191 4.080044 -1.050457"/>
    <point index="4" value=" -0.746821 4.080044 -0.671393"/>
    <point index="5" value=" 0.746821 4.080044 -0.671393"/>
    <point index="6" value=" 0.604191 4.980533 -1.050457"/>
    <point index="7" value=" 0.230780 4.980533 -1.284731"/>
    <point index="8" value=" -0.230781 4.980533 -1.284731"/>
    <point index="9" value=" -0.604191 4.980533 -1.050457"/>
    <point index="10" value=" -0.746821 4.980533 -0.671393"/>
    <point index="11" value=" -0.604191 4.980533 -0.292329"/>
    <point index="12" value=" -0.230780 4.980533 -0.058055"/>
    <point index="13" value=" 0.230780 4.980533 -0.058055"/>
    <point index="14" value=" 0.604191 4.980533 -0.292329"/>
    <point index="15" value=" 0.746821 4.980533 -0.671393"/>
    <point index="16" value=" 0.604191 5.881021 -1.050457"/>
    <point index="17" value=" 0.230780 5.881021 -1.284731"/>
    <point index="18" value=" -0.230781 5.881021 -1.284731"/>
    <point index="19" value=" -0.604191 5.881021 -1.050457"/>
    <point index="20" value=" -0.746821 5.881021 -0.671393"/>
    <point index="21" value=" -0.604191 5.881021 -0.292329"/>
    <point index="22" value=" -0.230780 5.881021 -0.058055"/>
    <point index="23" value=" 0.230780 5.881021 -0.058055"/>
    <point index="24" value=" 0.604191 5.881021 -0.292329"/>
    <point index="25" value=" 0.746821 5.881021 -0.671393"/>
    <point index="26" value=" 0.604191 6.781509 -1.050457"/>
    <point index="27" value=" 0.230780 6.781509 -1.284731"/>
    <point index="28" value=" -0.230781 6.781509 -1.284731"/>
    <point index="29" value=" -0.604191 6.781509 -1.050457"/>
    <point index="30" value=" -0.746821 6.781509 -0.671393"/>
    <point index="31" value=" -0.604191 6.781509 -0.292329"/>
    <point index="32" value=" -0.230780 6.781509 -0.058055"/>
    <point index="33" value=" 0.230780 6.781509 -0.058055"/>
    <point index="34" value=" 0.604191 6.781509 -0.292329"/>
    <point index="35" value=" 0.746821 6.781509 -0.671393"/>
    <point index="36" value=" 0.604191 7.681998 -1.050457"/>
    <point index="37" value=" 0.230780 7.681998 -1.284731"/>
    <point index="38" value=" -0.230781 7.681998 -1.284731"/>
    <point index="39" value=" -0.604191 7.681998 -1.050457"/>
    <point index="40" value=" -0.746821 7.681998 -0.671393"/>
    <point index="41" value=" -0.604191 7.681998 -0.292329"/>
    <point index="42" value=" -0.230780 7.681998 -0.058055"/>
    <point index="43" value=" 0.230780 7.681998 -0.058055"/>
    <point index="44" value=" 0.604191 7.681998 -0.292329"/>
    <point index="45" value=" 0.746821 7.681998 -0.671393"/>
    <point index="46" value=" 0.604191 8.582486 -1.050457"/>
    <point index="47" value=" 0.230780 8.582486 -1.284731"/>
    <point index="48" value=" -0.230781 8.582486 -1.284731"/>
    <point index="49" value=" -0.604191 8.582486 -1.050457"/>
    <point index="50" value=" -0.746821 8.582486 -0.671393"/>
    <point index="51" value=" -0.604191 8.582486 -0.292329"/>
    <point index="52" value=" -0.230780 8.582486 -0.058055"/>
    <point index="53" value=" 0.230780 8.582486 -0.058055"/>
    <point index="54" value=" 0.604191 8.582486 -0.292329"/>
    <point index="55" value=" 0.746821 8.582486 -0.671393"/>
    <point index="56" value=" 0.604191 9.482974 -1.050457"/>
    <point index="57" value=" 0.230780 9.482974 -1.284731"/>
    <point index="58" value=" -0.230781 9.482974 -1.284731"/>
    <point index="59" value=" -0.604191 9.482974 -1.050457"/>
    <point index="60" value=" -0.746821 9.482974 -0.671393"/>
    <point index="61" value=" -0.604191 9.482974 -0.292329"/>
    <point index="62" value=" -0.230780 9.482974 -0.058055"/>
    <point index="63" value=" 0.230780 9.482974 -0.058055"/>
    <point index="64" value=" 0.604191 9.482974 -0.292329"/>
    <point index="65" value=" 0.746821 9.482974 -0.671393"/>
    <point index="66" value=" 0.604191 10.383463 -1.050457"/>
    <point index="67" value=" 0.230780 10.383463 -1.284731"/>
    <point index="68" value=" -0.230781 10.383463 -1.284731"/>
    <point index="69" value=" -0.604191 10.383463 -1.050457"/>
    <point index="70" value=" -0.746821 10.383463 -0.671393"/>
    <point index="71" value=" -0.604191 10.383463 -0.292329"/>
    <point index="72" value=" -0.230780 10.383463 -0.058055"/>
    <point index="73" value=" 0.230780 10.383463 -0.058055"/>
    <point index="74" value=" 0.604191 10.383463 -0.292329"/>
    <point index="75" value=" 0.746821 10.383463 -0.671393"/>
    <point index="76" value=" 0.604191 11.283952 -1.050457"/>
    <point index="77" value=" 0.230780 11.283952 -1.284731"/>
    <point index="78" value=" -0.230781 11.283952 -1.284731"/>
    <point index="79" value=" -0.604191 11.283952 -1.050457"/>
    <point index="80" value=" -0.746821 11.283952 -0.671393"/>
    <point index="81" value=" -0.604191 11.283952 -0.292329"/>
    <point index="82" value=" -0.230780 11.283952 -0.058055"/>
    <point index="83" value=" 0.230780 11.283952 -0.058055"/>
    <point index="84" value=" 0.604191 11.283952 -0.292329"/>
    <point index="85" value=" 0.746821 11.283952 -0.671393"/>
    <point index="86" value=" 0.604191 12.184440 -1.050457"/>
    <point index="87" value=" 0.230780 12.184440 -1.284731"/>
    <point index="88" value=" -0.230781 12.184440 -1.284731"/>
    <point index="89" value=" -0.604191 12.184440 -1.050457"/>
    <point index="90" value=" -0.746821 12.184440 -0.671393"/>
    <point index="91" value=" -0.604191 12.184440 -0.292329"/>
    <point index="92" value=" -0.230780 12.184440 -0.058055"/>
    <point index="93" value=" 0.230780 12.184440 -0.058055"/>
    <point index="94" value=" 0.604191 12.184440 -0.292329"/>
    <point index="95" value=" 0.746821 12.184440 -0.671393"/>
    <point index="96" value=" 0.604191 13.084929 -1.050457"/>
    <point index="97" value=" 0.230780 13.084929 -1.284731"/>
    <point index="98" value=" -0.230781 13.084929 -1.284731"/>
    <point index="99" value=" -0.604191 13.084929 -1.050457"/>
    <point index="100" value=" -0.746821 13.084929 -0.671393"/>
    <point index="101" value=" -0.604191 13.084929 -0.292329"/>
    <point index="102" value=" -0.230780 13.084929 -0.058055"/>
    <point index="103" value=" 0.230780 13.084929 -0.058055"/>
    <point index="104" value=" 0.604191 13.084929 -0.292329"/>
    <point index="105" value=" 0.746821 13.084929 -0.671393"/>
    <point index="106" value=" 0.000000 4.080044 -0.671393"/>
    <point index="107" value=" 0.000000 13.084929 -0.671393"/>
    <point index="108" value=" -0.746821 4.080044 -0.671393"/>
    <point index="109" value=" -0.604191 4.080044 -0.292329"/>
    <point index="110" value=" -0.604191 4.980533 -0.292329"/>
    <point index="111" value=" -0.746821 4.980533 -0.671393"/>
    <point index="112" value=" -0.230780 4.080044 -0.058055"/>
    <point index="113" value=" -0.230780 4.980533 -0.058055"/>
    <point index="114" value=" 0.230780 4.080044 -0.058055"/>
    <point index="115" value=" 0.230780 4.980533 -0.058055"/>
    <point index="116" value=" 0.604191 4.080044 -0.292329"/>
    <point index="117" value=" 0.604191 4.980533 -0.292329"/>
    <point index="118" value=" 0.746821 4.080044 -0.671393"/>
    <point index="119" value=" 0.746821 4.980533 -0.671393"/>
    <point index="120" value=" 0.000000 4.080044 -0.671393"/>
    <point index="121" value=" -1.078675 4.530288 -0.671393"/>
    <point index="122" value=" -0.842596 4.080044 -0.671393"/>
    <point index="123" value=" -1.009529 4.211905 -0.671393"/>
    <point index="124" value=" -0.872666 4.530288 -0.136284"/>
    <point index="125" value=" -0.817174 4.211905 -0.171749"/>
    <point index="126" value=" -0.683204 4.080044 -0.257370"/>
    <point index="127" value=" -0.683204 4.980533 -0.257370"/>
    <point index="128" value=" -0.817174 4.848672 -0.171749"/>
    <point index="129" value=" -1.009529 4.848672 -0.671393"/>
    <point index="130" value=" -0.842596 4.980533 -0.671393"/>
    <point index="131" value=" -0.333329 4.530288 0.194432"/>
    <point index="132" value=" -0.312402 4.211905 0.137771"/>
    <point index="133" value=" -0.261880 4.080044 0.000980"/>
    <point index="134" value=" -0.261880 4.980533 0.000980"/>
    <point index="135" value=" -0.312402 4.848672 0.137771"/>
    <point index="136" value=" 0.333329 4.530288 0.194432"/>
    <point index="137" value=" 0.312402 4.211905 0.137771"/>
    <point index="138" value=" 0.261880 4.080044 0.000980"/>
    <point index="139" value=" 0.261880 4.980533 0.000980"/>
    <point index="140" value=" 0.312402 4.848672 0.137771"/>
    <point index="141" value=" 0.872666 4.530288 -0.136284"/>
    <point index="142" value=" 0.817174 4.211905 -0.171749"/>
    <point index="143" value=" 0.683204 4.080044 -0.257370"/>
    <point index="144" value=" 0.683204 4.980533 -0.257370"/>
    <point index="145" value=" 0.817174 4.848672 -0.171749"/>
    <point index="146" value=" 1.078675 4.530288 -0.671393"/>
    <point index="147" value=" 1.009529 4.211905 -0.671393"/>
    <point index="148" value=" 0.842596 4.080044 -0.671393"/>
    <point index="149" value=" 1.009529 4.848672 -0.671393"/>
    <point index="150" value=" 0.842596 4.980533 -0.671393"/>
    <point index="151" value=" 0.683204 5.881021 -1.085416"/>
    <point index="152" value=" 0.817174 6.012881 -1.171037"/>
    <point index="153" value=" 0.872666 6.331265 -1.206502"/>
    <point index="154" value=" 0.333329 6.331265 -1.537217"/>
    <point index="155" value=" 0.312402 6.012881 -1.480557"/>
    <point index="156" value=" 0.261880 5.881021 -1.343766"/>
    <point index="157" value=" 0.261880 6.781509 -1.343766"/>
    <point index="158" value=" 0.312402 6.649649 -1.480557"/>
    <point index="159" value=" 0.817174 6.649649 -1.171037"/>
    <point index="160" value=" 0.683204 6.781509 -1.085416"/>
    <point index="161" value=" -0.333329 6.331265 -1.537217"/>
    <point index="162" value=" -0.312402 6.012881 -1.480557"/>
    <point index="163" value=" -0.261880 5.881021 -1.343766"/>
    <point index="164" value=" -0.261880 6.781509 -1.343766"/>
    <point index="165" value=" -0.312402 6.649649 -1.480557"/>
    <point index="166" value=" -0.872666 6.331265 -1.206502"/>
    <point index="167" value=" -0.817174 6.012881 -1.171036"/>
    <point index="168" value=" -0.683204 5.881021 -1.085415"/>
    <point index="169" value=" -0.683204 6.781509 -1.085415"/>
    <point index="170" value=" -0.817174 6.649649 -1.171036"/>
    <point index="171" value=" -1.078675 6.331265 -0.671393"/>
    <point index="172" value=" -1.009529 6.012881 -0.671393"/>
    <point index="173" value=" -0.842596 5.881021 -0.671393"/>
    <point index="174" value=" -0.842596 6.781509 -0.671393"/>
    <point index="175" value=" -1.009529 6.649649 -0.671393"/>
    <point index="176" value=" -0.872666 6.331265 -0.136284"/>
    <point index="177" value=" -0.817174 6.012881 -0.171749"/>
    <point index="178" value=" -0.683204 5.881021 -0.257370"/>
    <point index="179" value=" -0.683204 6.781509 -0.257370"/>
    <point index="180" value=" -0.817174 6.649649 -0.171749"/>
    <point index="181" value=" -0.333329 6.331265 0.194432"/>
    <point index="182" value=" -0.312402 6.012881 0.137771"/>
    <point index="183" value=" -0.261880 5.881021 0.000980"/>
    <point index="184" value=" -0.261880 6.781509 0.000980"/>
    <point index="185" value=" -0.312402 6.649649 0.137771"/>
    <point index="186" value=" 0.333329 6.331265 0.194432"/>
    <point index="187" value=" 0.312402 6.012881 0.137771"/>
    <point index="188" value=" 0.261880 5.881021 0.000980"/>
    <point index="189" value=" 0.261880 6.781509 0.000980"/>
    <point index="190" value=" 0.312402 6.649649 0.137771"/>
    <point index="191" value=" 0.872666 6.331265 -0.136284"/>
    <point index="192" value=" 0.817174 6.012881 -0.171749"/>
    <point index="193" value=" 0.683204 5.881021 -0.257370"/>
    <point index="194" value=" 0.683204 6.781509 -0.257370"/>
    <point index="195" value=" 0.817174 6.649649 -0.171749"/>
    <point index="196" value=" 1.078675 6.331265 -0.671393"/>
    <point index="197" value=" 1.009529 6.012881 -0.671393"/>
    <point index="198" value=" 0.842596 5.881021 -0.671393"/>
    <point index="199" value=" 0.842596 6.781509 -0.671393"/>
    <point index="200" value=" 1.009529 6.649649 -0.671393"/>
    <point index="201" value=" 0.683204 7.681998 -1.085416"/>
    <point index="202" value=" 0.817174 7.813858 -1.171037"/>
    <point index="203" value=" 0.872666 8.132242 -1.206502"/>
    <point index="204" value=" 0.333329 8.132242 -1.537217"/>
    <point index="205" value=" 0.312402 7.813858 -1.480557"/>
    <point index="206" value=" 0.261880 7.681998 -1.343766"/>
    <point index="207" value=" 0.261880 8.582486 -1.343766"/>
    <point index="208" value=" 0.312402 8.450626 -1.480557"/>
    <point index="209" value=" 0.817174 8.450626 -1.171037"/>
    <point index="210" value=" 0.683204 8.582486 -1.085416"/>
    <point index="211" value=" -0.333329 8.132242 -1.537217"/>
    <point index="212" value=" -0.312402 7.813858 -1.480557"/>
    <point index="213" value=" -0.261880 7.681998 -1.343766"/>
    <point index="214" value=" -0.261880 8.582486 -1.343766"/>
    <point index="215" value=" -0.312402 8.450626 -1.480557"/>
    <point index="216" value=" -0.872666 8.132242 -1.206502"/>
    <point index="217" value=" -0.817174 7.813858 -1.171036"/>
    <point index="218" value=" -0.683204 7.681998 -1.085415"/>
    <point index="219" value=" -0.683204 8.582486 -1.085415"/>
    <point index="220" value=" -0.817174 8.450626 -1.171036"/>
    <point index="221" value=" -1.078675 8.132242 -0.671393"/>
    <point index="222" value=" -1.009529 7.813858 -0.671393"/>
    <point index="223" value=" -0.842596 7.681998 -0.671393"/>
    <point index="224" value=" -0.842596 8.582486 -0.671393"/>
    <point index="225" value=" -1.009529 8.450626 -0.671393"/>
    <point index="226" value=" -0.872666 8.132242 -0.136284"/>
    <point index="227" value=" -0.817174 7.813858 -0.171749"/>
    <point index="228" value=" -0.683204 7.681998 -0.257370"/>
    <point index="229" value=" -0.683204 8.582486 -0.257370"/>
    <point index="230" value=" -0.817174 8.450626 -0.171749"/>
    <point index="231" value=" -0.333329 8.132242 0.194432"/>
    <point index="232" value=" -0.312402 7.813858 0.137771"/>
    <point index="233" value=" -0.261880 7.681998 0.000980"/>
    <point index="234" value=" -0.261880 8.582486 0.000980"/>
    <point index="235" value=" -0.312402 8.450626 0.137771"/>
    <point index="236" value=" 0.333329 8.132242 0.194432"/>
    <point index="237" value=" 0.312402 7.813858 0.137771"/>
    <point index="238" value=" 0.261880 7.681998 0.000980"/>
    <point index="239" value=" 0.261880 8.582486 0.000980"/>
    <point index="240" value=" 0.312402 8.450626 0.137771"/>
    <point index="241" value=" 0.872666 8.132242 -0.136284"/>
    <point index="242" value=" 0.817174 7.813858 -0.171749"/>
    <point index="243" value=" 0.683204 7.681998 -0.257370"/>
    <point index="244" value=" 0.683204 8.582486 -0.257370"/>
    <point index="245" value=" 0.817174 8.450626 -0.171749"/>
    <point index="246" value=" 1.078675 8.132242 -0.671393"/>
    <point index="247" value=" 1.009529 7.813858 -0.671393"/>
    <point index="248" value=" 0.842596 7.681998 -0.671393"/>
    <point index="249" value=" 0.842596 8.582486 -0.671393"/>
    <point index="250" value=" 1.009529 8.450626 -0.671393"/>
    <point index="251" value=" 0.683204 9.482974 -1.085416"/>
    <point index="252" value=" 0.817174 9.614835 -1.171037"/>
    <point index="253" value=" 0.872666 9.933218 -1.206502"/>
    <point index="254" value=" 0.333329 9.933218 -1.537217"/>
    <point index="255" value=" 0.312402 9.614835 -1.480557"/>
    <point index="256" value=" 0.261880 9.482974 -1.343766"/>
    <point index="257" value=" 0.261880 10.383463 -1.343766"/>
    <point index="258" value=" 0.312402 10.251602 -1.480557"/>
    <point index="259" value=" 0.817174 10.251602 -1.171037"/>
    <point index="260" value=" 0.683204 10.383463 -1.085416"/>
    <point index="261" value=" -0.333329 9.933218 -1.537217"/>
    <point index="262" value=" -0.312402 9.614835 -1.480557"/>
    <point index="263" value=" -0.261880 9.482974 -1.343766"/>
    <point index="264" value=" -0.261880 10.383463 -1.343766"/>
    <point index="265" value=" -0.312402 10.251602 -1.480557"/>
    <point index="266" value=" -0.872666 9.933218 -1.206502"/>
    <point index="267" value=" -0.817174 9.614835 -1.171036"/>
    <point index="268" value=" -0.683204 9.482974 -1.085415"/>
    <point index="269" value=" -0.683204 10.383463 -1.085415"/>
    <point index="270" value=" -0.817174 10.251602 -1.171036"/>
    <point index="271" value=" -1.078675 9.933218 -0.671393"/>
    <point index="272" value=" -1.009529 9.614835 -0.671393"/>
    <point index="273" value=" -0.842596 9.482974 -0.671393"/>
    <point index="274" value=" -0.842596 10.383463 -0.671393"/>
    <point index="275" value=" -1.009529 10.251602 -0.671393"/>
    <point index="276" value=" -0.872666 9.933218 -0.136284"/>
    <point index="277" value=" -0.817174 9.614835 -0.171749"/>
    <point index="278" value=" -0.683204 9.482974 -0.257370"/>
    <point index="279" value=" -0.683204 10.383463 -0.257370"/>
    <point index="280" value=" -0.817174 10.251602 -0.171749"/>
    <point index="281" value=" -0.333329 9.933218 0.194432"/>
    <point index="282" value=" -0.312402 9.614835 0.137771"/>
    <point index="283" value=" -0.261880 9.482974 0.000980"/>
    <point index="284" value=" -0.261880 10.383463 0.000980"/>
    <point index="285" value=" -0.312402 10.251602 0.137771"/>
    <point index="286" value=" 0.333329 9.933218 0.194432"/>
    <point index="287" value=" 0.312402 9.614835 0.137771"/>
    <point index="288" value=" 0.261880 9.482974 0.000980"/>
    <point index="289" value=" 0.261880 10.383463 0.000980"/>
    <point index="290" value=" 0.312402 10.251602 0.137771"/>
    <point index="291" value=" 0.872666 9.933218 -0.136284"/>
    <point index="292" value=" 0.817174 9.614835 -0.171749"/>
    <point index="293" value=" 0.683204 9.482974 -0.257370"/>
    <point index="294" value=" 0.683204 10.383463 -0.257370"/>
    <point index="295" value=" 0.817174 10.251602 -0.171749"/>
    <point index="296" value=" 1.078675 9.933218 -0.671393"/>
    <point index="297" value=" 1.009529 9.614835 -0.671393"/>
    <point index="298" value=" 0.842596 9.482974 -0.671393"/>
    <point index="299" value=" 0.842596 10.383463 -0.671393"/>
    <point index="300" value=" 1.009529 10.251602 -0.671393"/>
    <point index="301" value=" 0.683204 11.283952 -1.085416"/>
    <point index="302" value=" 0.817174 11.415812 -1.171037"/>
    <point index="303" value=" 0.872666 11.734196 -1.206502"/>
    <point index="304" value=" 0.333329 11.734196 -1.537217"/>
    <point index="305" value=" 0.312402 11.415812 -1.480557"/>
    <point index="306" value=" 0.261880 11.283952 -1.343766"/>
    <point index="307" value=" 0.261880 12.184440 -1.343766"/>
    <point index="308" value=" 0.312402 12.052580 -1.480557"/>
    <point index="309" value=" 0.817174 12.052580 -1.171037"/>
    <point index="310" value=" 0.683204 12.184440 -1.085416"/>
    <point index="311" value=" -0.333329 11.734196 -1.537217"/>
    <point index="312" value=" -0.312402 11.415812 -1.480557"/>
    <point index="313" value=" -0.261880 11.283952 -1.343766"/>
    <point index="314" value=" -0.261880 12.184440 -1.343766"/>
    <point index="315" value=" -0.312402 12.052580 -1.480557"/>
    <point index="316" value=" -0.872666 11.734196 -1.206502"/>
    <point index="317" value=" -0.817174 11.415812 -1.171036"/>
    <point index="318" value=" -0.683204 11.283952 -1.085415"/>
    <point index="319" value=" -0.683204 12.184440 -1.085415"/>
    <point index="320" value=" -0.817174 12.052580 -1.171036"/>
    <point index="321" value=" -1.078675 11.734196 -0.671393"/>
    <point index="322" value=" -1.009529 11.415812 -0.671393"/>
    <point index="323" value=" -0.842596 11.283952 -0.671393"/>
    <point index="324" value=" -0.842596 12.184440 -0.671393"/>
    <point index="325" value=" -1.009529 12.052580 -0.671393"/>
    <point index="326" value=" -0.872666 11.734196 -0.136284"/>
    <point index="327" value=" -0.817174 11.415812 -0.171749"/>
    <point index="328" value=" -0.683204 11.283952 -0.257370"/>
    <point index="329" value=" -0.683204 12.184440 -0.257370"/>
    <point index="330" value=" -0.817174 12.052580 -0.171749"/>
    <point index="331" value=" -0.333329 11.734196 0.194432"/>
    <point index="332" value=" -0.312402 11.415812 0.137771"/>
    <point index="333" value=" -0.261880 11.283952 0.000980"/>
    <point index="334" value=" -0.261880 12.184440 0.000980"/>
    <point index="335" value=" -0.312402 12.052580 0.137771"/>
    <point index="336" value=" 0.333329 11.734196 0.194432"/>
    <point index="337" value=" 0.312402 11.415812 0.137771"/>
    <point index="338" value=" 0.261880 11.283952 0.000980"/>
    <point index="339" value=" 0.261880 12.184440 0.000980"/>
    <point index="340" value=" 0.312402 12.052580 0.137771"/>
    <point index="341" value=" 0.872666 11.734196 -0.136284"/>
    <point index="342" value=" 0.817174 11.415812 -0.171749"/>
    <point index="343" value=" 0.683204 11.283952 -0.257370"/>
    <point index="344" value=" 0.683204 12.184440 -0.257370"/>
    <point index="345" value=" 0.817174 12.052580 -0.171749"/>
    <point index="346" value=" 1.078675 11.734196 -0.671393"/>
    <point index="347" value=" 1.009529 11.415812 -0.671393"/>
    <point index="348" value=" 0.842596 11.283952 -0.671393"/>
    <point index="349" value=" 0.842596 12.184440 -0.671393"/>
    <point index="350" value=" 1.009529 12.052580 -0.671393"/>
    <point index="351" value=" 0.683204 4.080044 -1.085416"/>
    <point index="352" value=" 0.805402 4.239876 -1.163513"/>
    <point index="353" value=" 0.872666 4.530288 -1.206502"/>
    <point index="354" value=" 0.333329 4.530288 -1.537217"/>
    <point index="355" value=" 0.307963 4.239876 -1.468537"/>
    <point index="356" value=" 0.261880 4.080044 -1.343766"/>
    <point index="357" value=" 0.261880 4.980533 -1.343766"/>
    <point index="358" value=" 0.307963 4.820701 -1.468537"/>
    <point index="359" value=" 0.805402 4.820701 -1.163513"/>
    <point index="360" value=" 0.683204 4.980533 -1.085416"/>
    <point index="361" value=" -0.333329 4.530288 -1.537217"/>
    <point index="362" value=" -0.307963 4.239876 -1.468537"/>
    <point index="363" value=" -0.261880 4.080044 -1.343766"/>
    <point index="364" value=" -0.261880 4.980533 -1.343766"/>
    <point index="365" value=" -0.307963 4.820701 -1.468537"/>
    <point index="366" value=" -0.872666 4.530288 -1.206502"/>
    <point index="367" value=" -0.805402 4.239876 -1.163513"/>
    <point index="368" value=" -0.683204 4.080044 -1.085415"/>
    <point index="369" value=" -0.683204 4.980533 -1.085415"/>
    <point index="370" value=" -0.805402 4.820701 -1.163513"/>
    <point index="371" value=" -1.078675 4.530288 -0.671393"/>
    <point index="372" value=" -0.994861 4.239876 -0.671393"/>
    <point index="373" value=" -0.842596 4.080044 -0.671393"/>
    <point index="374" value=" -0.994861 4.820701 -0.671393"/>
    <point index="375" value=" -0.842596 4.980533 -0.671393"/>
    <point index="376" value=" 1.078675 4.530288 -0.671393"/>
    <point index="377" value=" 0.842596 4.080044 -0.671393"/>
    <point index="378" value=" 0.994861 4.239876 -0.671393"/>
    <point index="379" value=" 0.994861 4.820701 -0.671393"/>
    <point index="380" value=" 0.842596 4.980533 -0.671393"/>
    <point index="381" value=" 0.751557 5.156355 -1.142913"/>
    <point index="382" value=" 0.809100 5.377303 -1.179015"/>
    <point index="383" value=" 0.309049 5.377303 -1.492742"/>
    <point index="384" value=" 0.287069 5.156355 -1.434329"/>
    <point index="385" value=" 0.289999 5.615154 -1.442114"/>
    <point index="386" value=" 0.309049 5.384035 -1.492742"/>
    <point index="387" value=" 0.809100 5.384035 -1.179015"/>
    <point index="388" value=" 0.759227 5.615154 -1.147725"/>
    <point index="389" value=" -0.309049 5.377303 -1.492742"/>
    <point index="390" value=" -0.287069 5.156355 -1.434328"/>
    <point index="391" value=" -0.289999 5.615154 -1.442114"/>
    <point index="392" value=" -0.309049 5.384035 -1.492742"/>
    <point index="393" value=" -0.809100 5.377303 -1.179015"/>
    <point index="394" value=" -0.751557 5.156355 -1.142913"/>
    <point index="395" value=" -0.759227 5.615154 -1.147725"/>
    <point index="396" value=" -0.809100 5.384035 -1.179015"/>
    <point index="397" value=" -1.000103 5.377303 -0.671393"/>
    <point index="398" value=" -0.928976 5.156355 -0.671393"/>
    <point index="399" value=" -0.938456 5.615154 -0.671393"/>
    <point index="400" value=" -1.000103 5.384035 -0.671393"/>
    <point index="401" value=" -0.809100 5.377303 -0.163771"/>
    <point index="402" value=" -0.751557 5.156355 -0.199873"/>
    <point index="403" value=" -0.759227 5.615154 -0.195061"/>
    <point index="404" value=" -0.809100 5.384035 -0.163771"/>
    <point index="405" value=" -0.309049 5.377303 0.149957"/>
    <point index="406" value=" -0.287069 5.156355 0.091543"/>
    <point index="407" value=" -0.289999 5.615154 0.099328"/>
    <point index="408" value=" -0.309049 5.384035 0.149957"/>
    <point index="409" value=" 0.309049 5.377303 0.149957"/>
    <point index="410" value=" 0.287069 5.156355 0.091543"/>
    <point index="411" value=" 0.289999 5.615154 0.099328"/>
    <point index="412" value=" 0.309049 5.384035 0.149957"/>
    <point index="413" value=" 0.809100 5.377303 -0.163771"/>
    <point index="414" value=" 0.751557 5.156355 -0.199873"/>
    <point index="415" value=" 0.759227 5.615154 -0.195061"/>
    <point index="416" value=" 0.809100 5.384035 -0.163771"/>
    <point index="417" value=" 1.000103 5.377303 -0.671393"/>
    <point index="418" value=" 0.928976 5.156355 -0.671393"/>
    <point index="419" value=" 0.938456 5.615154 -0.671393"/>
    <point index="420" value=" 1.000103 5.384035 -0.671393"/>
    <point index="421" value=" 0.753582 6.979235 -1.144183"/>
    <point index="422" value=" 0.809100 7.203055 -1.179015"/>
    <point index="423" value=" 0.309049 7.203055 -1.492743"/>
    <point index="424" value=" 0.287843 6.979235 -1.436384"/>
    <point index="425" value=" 0.289308 7.439217 -1.440280"/>
    <point index="426" value=" 0.309049 7.210325 -1.492743"/>
    <point index="427" value=" 0.809100 7.210325 -1.179015"/>
    <point index="428" value=" 0.757420 7.439217 -1.146591"/>
    <point index="429" value=" -0.309049 7.203055 -1.492742"/>
    <point index="430" value=" -0.287843 6.979235 -1.436384"/>
    <point index="431" value=" -0.289309 7.439217 -1.440279"/>
    <point index="432" value=" -0.309049 7.210325 -1.492742"/>
    <point index="433" value=" -0.809100 7.203055 -1.179015"/>
    <point index="434" value=" -0.753582 6.979235 -1.144183"/>
    <point index="435" value=" -0.757420 7.439217 -1.146591"/>
    <point index="436" value=" -0.809100 7.210325 -1.179015"/>
    <point index="437" value=" -1.000103 7.203055 -0.671393"/>
    <point index="438" value=" -0.931478 6.979235 -0.671393"/>
    <point index="439" value=" -0.936222 7.439217 -0.671393"/>
    <point index="440" value=" -1.000103 7.210325 -0.671393"/>
    <point index="441" value=" -0.809100 7.203055 -0.163771"/>
    <point index="442" value=" -0.753582 6.979235 -0.198602"/>
    <point index="443" value=" -0.757420 7.439217 -0.196195"/>
    <point index="444" value=" -0.809100 7.210325 -0.163771"/>
    <point index="445" value=" -0.309049 7.203055 0.149957"/>
    <point index="446" value=" -0.287843 6.979235 0.093598"/>
    <point index="447" value=" -0.289308 7.439217 0.097494"/>
    <point index="448" value=" -0.309049 7.210325 0.149957"/>
    <point index="449" value=" 0.309049 7.203055 0.149957"/>
    <point index="450" value=" 0.287843 6.979235 0.093598"/>
    <point index="451" value=" 0.289309 7.439217 0.097494"/>
    <point index="452" value=" 0.309049 7.210325 0.149957"/>
    <point index="453" value=" 0.809100 7.203055 -0.163771"/>
    <point index="454" value=" 0.753582 6.979235 -0.198602"/>
    <point index="455" value=" 0.757420 7.439217 -0.196195"/>
    <point index="456" value=" 0.809100 7.210325 -0.163771"/>
    <point index="457" value=" 1.000103 7.203055 -0.671393"/>
    <point index="458" value=" 0.931478 6.979235 -0.671393"/>
    <point index="459" value=" 0.936222 7.439217 -0.671393"/>
    <point index="460" value=" 1.000103 7.210325 -0.671393"/>
    <point index="461" value=" 0.755537 8.802542 -1.145410"/>
    <point index="462" value=" 0.809100 9.029006 -1.179015"/>
    <point index="463" value=" 0.309049 9.029006 -1.492742"/>
    <point index="464" value=" 0.288589 8.802542 -1.438369"/>
    <point index="465" value=" 0.288589 9.262919 -1.438369"/>
    <point index="466" value=" 0.309049 9.036455 -1.492742"/>
    <point index="467" value=" 0.809100 9.036455 -1.179015"/>
    <point index="468" value=" 0.755537 9.262919 -1.145410"/>
    <point index="469" value=" -0.309049 9.029006 -1.492742"/>
    <point index="470" value=" -0.288590 8.802542 -1.438369"/>
    <point index="471" value=" -0.288590 9.262919 -1.438369"/>
    <point index="472" value=" -0.309049 9.036455 -1.492742"/>
    <point index="473" value=" -0.809100 9.029006 -1.179015"/>
    <point index="474" value=" -0.755537 8.802542 -1.145410"/>
    <point index="475" value=" -0.755537 9.262919 -1.145410"/>
    <point index="476" value=" -0.809100 9.036455 -1.179015"/>
    <point index="477" value=" -1.000103 9.029006 -0.671393"/>
    <point index="478" value=" -0.933895 8.802542 -0.671393"/>
    <point index="479" value=" -0.933895 9.262919 -0.671393"/>
    <point index="480" value=" -1.000103 9.036455 -0.671393"/>
    <point index="481" value=" -0.809100 9.029006 -0.163771"/>
    <point index="482" value=" -0.755537 8.802542 -0.197376"/>
    <point index="483" value=" -0.755537 9.262919 -0.197376"/>
    <point index="484" value=" -0.809100 9.036455 -0.163771"/>
    <point index="485" value=" -0.309049 9.029006 0.149957"/>
    <point index="486" value=" -0.288589 8.802542 0.095583"/>
    <point index="487" value=" -0.288589 9.262919 0.095583"/>
    <point index="488" value=" -0.309049 9.036455 0.149957"/>
    <point index="489" value=" 0.309049 9.029006 0.149957"/>
    <point index="490" value=" 0.288590 8.802542 0.095583"/>
    <point index="491" value=" 0.288590 9.262919 0.095583"/>
    <point index="492" value=" 0.309049 9.036455 0.149957"/>
    <point index="493" value=" 0.809100 9.029006 -0.163771"/>
    <point index="494" value=" 0.755537 8.802542 -0.197376"/>
    <point index="495" value=" 0.755537 9.262919 -0.197376"/>
    <point index="496" value=" 0.809100 9.036455 -0.163771"/>
    <point index="497" value=" 1.000103 9.029006 -0.671393"/>
    <point index="498" value=" 0.933895 8.802542 -0.671393"/>
    <point index="499" value=" 0.933895 9.262919 -0.671393"/>
    <point index="500" value=" 1.000103 9.036455 -0.671393"/>
    <point index="501" value=" 0.757420 10.626243 -1.146591"/>
    <point index="502" value=" 0.809100 10.855134 -1.179015"/>
    <point index="503" value=" 0.309049 10.855134 -1.492743"/>
    <point index="504" value=" 0.289308 10.626243 -1.440280"/>
    <point index="505" value=" 0.287843 11.086226 -1.436384"/>
    <point index="506" value=" 0.309049 10.862407 -1.492743"/>
    <point index="507" value=" 0.809100 10.862407 -1.179015"/>
    <point index="508" value=" 0.753582 11.086226 -1.144183"/>
    <point index="509" value=" -0.309049 10.855134 -1.492742"/>
    <point index="510" value=" -0.289309 10.626243 -1.440279"/>
    <point index="511" value=" -0.287843 11.086226 -1.436383"/>
    <point index="512" value=" -0.309049 10.862407 -1.492742"/>
    <point index="513" value=" -0.809100 10.855134 -1.179015"/>
    <point index="514" value=" -0.757420 10.626243 -1.146591"/>
    <point index="515" value=" -0.753582 11.086226 -1.144183"/>
    <point index="516" value=" -0.809100 10.862407 -1.179015"/>
    <point index="517" value=" -1.000103 10.855134 -0.671393"/>
    <point index="518" value=" -0.936222 10.626243 -0.671393"/>
    <point index="519" value=" -0.931478 11.086226 -0.671393"/>
    <point index="520" value=" -1.000103 10.862407 -0.671393"/>
    <point index="521" value=" -0.809100 10.855134 -0.163771"/>
    <point index="522" value=" -0.757420 10.626243 -0.196195"/>
    <point index="523" value=" -0.753582 11.086226 -0.198602"/>
    <point index="524" value=" -0.809100 10.862407 -0.163771"/>
    <point index="525" value=" -0.309049 10.855134 0.149957"/>
    <point index="526" value=" -0.289308 10.626243 0.097494"/>
    <point index="527" value=" -0.287843 11.086226 0.093598"/>
    <point index="528" value=" -0.309049 10.862407 0.149957"/>
    <point index="529" value=" 0.309049 10.855134 0.149957"/>
    <point index="530" value=" 0.289309 10.626243 0.097494"/>
    <point index="531" value=" 0.287843 11.086226 0.093598"/>
    <point index="532" value=" 0.309049 10.862407 0.149957"/>
    <point index="533" value=" 0.809100 10.855134 -0.163771"/>
    <point index="534" value=" 0.757420 10.626243 -0.196195"/>
    <point index="535" value=" 0.753582 11.086226 -0.198603"/>
    <point index="536" value=" 0.809100 10.862407 -0.163771"/>
    <point index="537" value=" 1.000103 10.855134 -0.671393"/>
    <point index="538" value=" 0.936222 10.626243 -0.671393"/>
    <point index="539" value=" 0.931478 11.086226 -0.671393"/>
    <point index="540" value=" 1.000103 10.862407 -0.671393"/>
    <point index="541" value=" 0.759227 12.450306 -1.147725"/>
    <point index="542" value=" 0.809100 12.681425 -1.179015"/>
    <point index="543" value=" 0.309049 12.681425 -1.492743"/>
    <point index="544" value=" 0.289999 12.450306 -1.442114"/>
    <point index="545" value=" 0.287069 12.909105 -1.434329"/>
    <point index="546" value=" 0.309049 12.688158 -1.492743"/>
    <point index="547" value=" 0.809100 12.688158 -1.179015"/>
    <point index="548" value=" 0.751557 12.909105 -1.142913"/>
    <point index="549" value=" -0.309049 12.681425 -1.492742"/>
    <point index="550" value=" -0.289999 12.450306 -1.442114"/>
    <point index="551" value=" -0.287069 12.909105 -1.434328"/>
    <point index="552" value=" -0.309049 12.688158 -1.492742"/>
    <point index="553" value=" -0.809100 12.681425 -1.179015"/>
    <point index="554" value=" -0.759227 12.450306 -1.147725"/>
    <point index="555" value=" -0.751557 12.909105 -1.142913"/>
    <point index="556" value=" -0.809100 12.688158 -1.179015"/>
    <point index="557" value=" -1.000103 12.681425 -0.671393"/>
    <point index="558" value=" -0.938456 12.450306 -0.671393"/>
    <point index="559" value=" -0.928976 12.909105 -0.671393"/>
    <point index="560" value=" -1.000103 12.688158 -0.671393"/>
    <point index="561" value=" -0.809100 12.681425 -0.163771"/>
    <point index="562" value=" -0.759227 12.450306 -0.195061"/>
    <point index="563" value=" -0.751557 12.909105 -0.199873"/>
    <point index="564" value=" -0.809100 12.688158 -0.163771"/>
    <point index="565" value=" -0.309049 12.681425 0.149957"/>
    <point index="566" value=" -0.289999 12.450306 0.099328"/>
    <point index="567" value=" -0.287069 12.909105 0.091543"/>
    <point index="568" value=" -0.309049 12.688158 0.149957"/>
    <point index="569" value=" 0.309049 12.681425 0.149957"/>
    <point index="570" value=" 0.289999 12.450306 0.099328"/>
    <point index="571" value=" 0.287069 12.909105 0.091543"/>
    <point index="572" value=" 0.309049 12.688158 0.149957"/>
    <point index="573" value=" 0.809100 12.681425 -0.163771"/>
    <point index="574" value=" 0.759227 12.450306 -0.195061"/>
    <point index="575" value=" 0.751557 12.909105 -0.199873"/>
    <point index="576" value=" 0.809100 12.688158 -0.163771"/>
    <point index="577" value=" 1.000103 12.681425 -0.671393"/>
    <point index="578" value=" 0.938456 12.450306 -0.671393"/>
    <point index="579" value=" 0.928976 12.909105 -0.671393"/>
    <point index="580" value=" 1.000103 12.688158 -0.671393"/>
    <point index="581" value=" 0.645566 -0.488255 -1.050457"/>
    <point index="582" value=" 0.272156 -0.488255 -1.284731"/>
    <point index="583" value=" -0.189405 -0.488255 -1.284731"/>
    <point index="584" value=" -0.562816 -0.488255 -1.050457"/>
    <point index="585" value=" -0.705446 -0.488255 -0.671393"/>
    <point index="586" value=" 0.788196 -0.488255 -0.671393"/>
    <point index="587" value=" 0.645566 0.412233 -1.050457"/>
    <point index="588" value=" 0.272156 0.412233 -1.284731"/>
    <point index="589" value=" -0.189405 0.412233 -1.284731"/>
    <point index="590" value=" -0.562816 0.412233 -1.050457"/>
    <point index="591" value=" -0.705446 0.412233 -0.671393"/>
    <point index="592" value=" -0.562816 0.412233 -0.292329"/>
    <point index="593" value=" -0.189405 0.412233 -0.058055"/>
    <point index="594" value=" 0.272156 0.412233 -0.058055"/>
    <point index="595" value=" 0.645566 0.412233 -0.292329"/>
    <point index="596" value=" 0.788196 0.412233 -0.671393"/>
    <point index="597" value=" 0.645566 1.312721 -1.050457"/>
    <point index="598" value=" 0.272156 1.312721 -1.284731"/>
    <point index="599" value=" -0.189405 1.312721 -1.284731"/>
    <point index="600" value=" -0.562816 1.312721 -1.050457"/>
    <point index="601" value=" -0.705446 1.312721 -0.671393"/>
    <point index="602" value=" -0.562816 1.312721 -0.292329"/>
    <point index="603" value=" -0.189405 1.312721 -0.058055"/>
    <point index="604" value=" 0.272156 1.312721 -0.058055"/>
    <point index="605" value=" 0.645566 1.312721 -0.292329"/>
    <point index="606" value=" 0.788196 1.312721 -0.671393"/>
    <point index="607" value=" 0.645566 2.213210 -1.050457"/>
    <point index="608" value=" 0.272156 2.213210 -1.284731"/>
    <point index="609" value=" -0.189405 2.213210 -1.284731"/>
    <point index="610" value=" -0.562816 2.213210 -1.050457"/>
    <point index="611" value=" -0.705446 2.213210 -0.671393"/>
    <point index="612" value=" -0.562816 2.213210 -0.292329"/>
    <point index="613" value=" -0.189405 2.213210 -0.058055"/>
    <point index="614" value=" 0.272156 2.213210 -0.058055"/>
    <point index="615" value=" 0.645566 2.213210 -0.292329"/>
    <point index="616" value=" 0.788196 2.213210 -0.671393"/>
    <point index="617" value=" 0.645566 3.113698 -1.050457"/>
    <point index="618" value=" 0.272156 3.113698 -1.284731"/>
    <point index="619" value=" -0.189405 3.113698 -1.284731"/>
    <point index="620" value=" -0.562816 3.113698 -1.050457"/>
    <point index="621" value=" -0.705446 3.113698 -0.671393"/>
    <point index="622" value=" -0.562816 3.113698 -0.292329"/>
    <point index="623" value=" -0.189405 3.113698 -0.058055"/>
    <point index="624" value=" 0.272156 3.113698 -0.058055"/>
    <point index="625" value=" 0.645566 3.113698 -0.292329"/>
    <point index="626" value=" 0.788196 3.113698 -0.671393"/>
    <point index="627" value=" 0.041375 -0.488255 -0.671393"/>
    <point index="628" value=" -0.705446 -0.488255 -0.671393"/>
    <point index="629" value=" -0.562816 -0.488255 -0.292329"/>
    <point index="630" value=" -0.562816 0.412233 -0.292329"/>
    <point index="631" value=" -0.705446 0.412233 -0.671393"/>
    <point index="632" value=" -0.189405 -0.488255 -0.058055"/>
    <point index="633" value=" -0.189405 0.412233 -0.058055"/>
    <point index="634" value=" 0.272156 -0.488255 -0.058055"/>
    <point index="635" value=" 0.272156 0.412233 -0.058055"/>
    <point index="636" value=" 0.645566 -0.488255 -0.292329"/>
    <point index="637" value=" 0.645566 0.412233 -0.292329"/>
    <point index="638" value=" 0.788196 -0.488255 -0.671393"/>
    <point index="639" value=" 0.788196 0.412233 -0.671393"/>
    <point index="640" value=" 0.041375 -0.488255 -0.671393"/>
    <point index="641" value=" -1.037300 -0.038011 -0.671393"/>
    <point index="642" value=" -0.801221 -0.488255 -0.671393"/>
    <point index="643" value=" -0.968154 -0.356395 -0.671393"/>
    <point index="644" value=" -0.831291 -0.038011 -0.136284"/>
    <point index="645" value=" -0.775799 -0.356395 -0.171749"/>
    <point index="646" value=" -0.641828 -0.488255 -0.257370"/>
    <point index="647" value=" -0.641828 0.412233 -0.257370"/>
    <point index="648" value=" -0.775799 0.280373 -0.171749"/>
    <point index="649" value=" -0.968154 0.280373 -0.671393"/>
    <point index="650" value=" -0.801221 0.412233 -0.671393"/>
    <point index="651" value=" -0.291953 -0.038011 0.194432"/>
    <point index="652" value=" -0.271027 -0.356395 0.137771"/>
    <point index="653" value=" -0.220505 -0.488255 0.000980"/>
    <point index="654" value=" -0.220505 0.412233 0.000980"/>
    <point index="655" value=" -0.271027 0.280373 0.137771"/>
    <point index="656" value=" 0.374704 -0.038011 0.194432"/>
    <point index="657" value=" 0.353777 -0.356395 0.137771"/>
    <point index="658" value=" 0.303256 -0.488255 0.000980"/>
    <point index="659" value=" 0.303256 0.412233 0.000980"/>
    <point index="660" value=" 0.353777 0.280373 0.137771"/>
    <point index="661" value=" 0.914042 -0.038011 -0.136284"/>
    <point index="662" value=" 0.858549 -0.356395 -0.171749"/>
    <point index="663" value=" 0.724579 -0.488255 -0.257370"/>
    <point index="664" value=" 0.724579 0.412233 -0.257370"/>
    <point index="665" value=" 0.858549 0.280373 -0.171749"/>
    <point index="666" value=" 1.120050 -0.038011 -0.671393"/>
    <point index="667" value=" 1.050904 -0.356395 -0.671393"/>
    <point index="668" value=" 0.883971 -0.488255 -0.671393"/>
    <point index="669" value=" 1.050904 0.280373 -0.671393"/>
    <point index="670" value=" 0.883971 0.412233 -0.671393"/>
    <point index="671" value=" 0.724579 1.312721 -1.085416"/>
    <point index="672" value=" 0.858549 1.444582 -1.171037"/>
    <point index="673" value=" 0.914042 1.762966 -1.206502"/>
    <point index="674" value=" 0.374704 1.762966 -1.537217"/>
    <point index="675" value=" 0.353777 1.444582 -1.480557"/>
    <point index="676" value=" 0.303256 1.312721 -1.343766"/>
    <point index="677" value=" 0.303256 2.213210 -1.343766"/>
    <point index="678" value=" 0.353777 2.081350 -1.480557"/>
    <point index="679" value=" 0.858549 2.081350 -1.171037"/>
    <point index="680" value=" 0.724579 2.213210 -1.085416"/>
    <point index="681" value=" -0.291954 1.762966 -1.537217"/>
    <point index="682" value=" -0.271027 1.444582 -1.480557"/>
    <point index="683" value=" -0.220505 1.312721 -1.343766"/>
    <point index="684" value=" -0.220505 2.213210 -1.343766"/>
    <point index="685" value=" -0.271027 2.081350 -1.480557"/>
    <point index="686" value=" -0.831291 1.762966 -1.206502"/>
    <point index="687" value=" -0.775799 1.444582 -1.171036"/>
    <point index="688" value=" -0.641828 1.312721 -1.085415"/>
    <point index="689" value=" -0.641828 2.213210 -1.085415"/>
    <point index="690" value=" -0.775799 2.081350 -1.171036"/>
    <point index="691" value=" -1.037300 1.762966 -0.671393"/>
    <point index="692" value=" -0.968154 1.444582 -0.671393"/>
    <point index="693" value=" -0.801221 1.312721 -0.671393"/>
    <point index="694" value=" -0.801221 2.213210 -0.671393"/>
    <point index="695" value=" -0.968154 2.081350 -0.671393"/>
    <point index="696" value=" -0.831291 1.762966 -0.136284"/>
    <point index="697" value=" -0.775799 1.444582 -0.171749"/>
    <point index="698" value=" -0.641828 1.312721 -0.257370"/>
    <point index="699" value=" -0.641828 2.213210 -0.257370"/>
    <point index="700" value=" -0.775799 2.081350 -0.171749"/>
    <point index="701" value=" -0.291953 1.762966 0.194432"/>
    <point index="702" value=" -0.271027 1.444582 0.137771"/>
    <point index="703" value=" -0.220505 1.312721 0.000980"/>
    <point index="704" value=" -0.220505 2.213210 0.000980"/>
    <point index="705" value=" -0.271027 2.081350 0.137771"/>
    <point index="706" value=" 0.374704 1.762966 0.194432"/>
    <point index="707" value=" 0.353777 1.444582 0.137771"/>
    <point index="708" value=" 0.303256 1.312721 0.000980"/>
    <point index="709" value=" 0.303256 2.213210 0.000980"/>
    <point index="710" value=" 0.353777 2.081350 0.137771"/>
    <point index="711" value=" 0.914042 1.762966 -0.136284"/>
    <point index="712" value=" 0.858549 1.444582 -0.171749"/>
    <point index="713" value=" 0.724579 1.312721 -0.257370"/>
    <point index="714" value=" 0.724579 2.213210 -0.257370"/>
    <point index="715" value=" 0.858549 2.081350 -0.171749"/>
    <point index="716" value=" 1.120050 1.762966 -0.671393"/>
    <point index="717" value=" 1.050904 1.444582 -0.671393"/>
    <point index="718" value=" 0.883971 1.312721 -0.671393"/>
    <point index="719" value=" 0.883971 2.213210 -0.671393"/>
    <point index="720" value=" 1.050904 2.081350 -0.671393"/>
    <point index="721" value=" 0.724579 3.113698 -1.085416"/>
    <point index="722" value=" 0.858549 3.245559 -1.171037"/>
    <point index="723" value=" 0.914042 3.563943 -1.206502"/>
    <point index="724" value=" 0.374704 3.563943 -1.537217"/>
    <point index="725" value=" 0.353777 3.245559 -1.480557"/>
    <point index="726" value=" 0.303256 3.113698 -1.343766"/>
    <point index="727" value=" 0.353777 3.882327 -1.480557"/>
    <point index="728" value=" 0.858549 3.882327 -1.171037"/>
    <point index="729" value=" -0.291954 3.563943 -1.537217"/>
    <point index="730" value=" -0.271027 3.245559 -1.480557"/>
    <point index="731" value=" -0.220505 3.113698 -1.343766"/>
    <point index="732" value=" -0.271027 3.882327 -1.480557"/>
    <point index="733" value=" -0.831291 3.563943 -1.206502"/>
    <point index="734" value=" -0.775799 3.245559 -1.171036"/>
    <point index="735" value=" -0.641828 3.113698 -1.085415"/>
    <point index="736" value=" -0.775799 3.882327 -1.171036"/>
    <point index="737" value=" -1.037300 3.563943 -0.671393"/>
    <point index="738" value=" -0.968154 3.245559 -0.671393"/>
    <point index="739" value=" -0.801221 3.113698 -0.671393"/>
    <point index="740" value=" -0.968154 3.882327 -0.671393"/>
    <point index="741" value=" -0.831291 3.563943 -0.136284"/>
    <point index="742" value=" -0.775799 3.245559 -0.171749"/>
    <point index="743" value=" -0.641828 3.113698 -0.257370"/>
    <point index="744" value=" -0.775799 3.882327 -0.171749"/>
    <point index="745" value=" -0.291953 3.563943 0.194432"/>
    <point index="746" value=" -0.271027 3.245559 0.137771"/>
    <point index="747" value=" -0.220505 3.113698 0.000980"/>
    <point index="748" value=" -0.271027 3.882327 0.137771"/>
    <point index="749" value=" 0.374704 3.563943 0.194432"/>
    <point index="750" value=" 0.353777 3.245559 0.137771"/>
    <point index="751" value=" 0.303256 3.113698 0.000980"/>
    <point index="752" value=" 0.353777 3.882327 0.137771"/>
    <point index="753" value=" 0.914042 3.563943 -0.136284"/>
    <point index="754" value=" 0.858549 3.245559 -0.171749"/>
    <point index="755" value=" 0.724579 3.113698 -0.257370"/>
    <point index="756" value=" 0.858549 3.882327 -0.171749"/>
    <point index="757" value=" 1.120050 3.563943 -0.671393"/>
    <point index="758" value=" 1.050904 3.245559 -0.671393"/>
    <point index="759" value=" 0.883971 3.113698 -0.671393"/>
    <point index="760" value=" 1.050904 3.882327 -0.671393"/>
    <point index="761" value=" 0.724579 -0.488255 -1.085416"/>
    <point index="762" value=" 0.846777 -0.328423 -1.163513"/>
    <point index="763" value=" 0.914042 -0.038011 -1.206502"/>
    <point index="764" value=" 0.374704 -0.038011 -1.537217"/>
    <point index="765" value=" 0.349338 -0.328423 -1.468537"/>
    <point index="766" value=" 0.303256 -0.488255 -1.343766"/>
    <point index="767" value=" 0.303256 0.412233 -1.343766"/>
    <point index="768" value=" 0.349338 0.252401 -1.468537"/>
    <point index="769" value=" 0.846777 0.252401 -1.163513"/>
    <point index="770" value=" 0.724579 0.412233 -1.085416"/>
    <point index="771" value=" -0.291954 -0.038011 -1.537217"/>
    <point index="772" value=" -0.266588 -0.328423 -1.468537"/>
    <point index="773" value=" -0.220505 -0.488255 -1.343766"/>
    <point index="774" value=" -0.220505 0.412233 -1.343766"/>
    <point index="775" value=" -0.266588 0.252401 -1.468537"/>
    <point index="776" value=" -0.831291 -0.038011 -1.206502"/>
    <point index="777" value=" -0.764027 -0.328423 -1.163513"/>
    <point index="778" value=" -0.641828 -0.488255 -1.085415"/>
    <point index="779" value=" -0.641828 0.412233 -1.085415"/>
    <point index="780" value=" -0.764027 0.252401 -1.163513"/>
    <point index="781" value=" -1.037300 -0.038011 -0.671393"/>
    <point index="782" value=" -0.953486 -0.328423 -0.671393"/>
    <point index="783" value=" -0.801221 -0.488255 -0.671393"/>
    <point index="784" value=" -0.953486 0.252401 -0.671393"/>
    <point index="785" value=" -0.801221 0.412233 -0.671393"/>
    <point index="786" value=" 1.120050 -0.038011 -0.671393"/>
    <point index="787" value=" 0.883971 -0.488255 -0.671393"/>
    <point index="788" value=" 1.036236 -0.328423 -0.671393"/>
    <point index="789" value=" 1.036236 0.252401 -0.671393"/>
    <point index="790" value=" 0.883971 0.412233 -0.671393"/>
    <point index="791" value=" 0.792933 0.588056 -1.142913"/>
    <point index="792" value=" 0.850475 0.809004 -1.179015"/>
    <point index="793" value=" 0.350424 0.809004 -1.492742"/>
    <point index="794" value=" 0.328445 0.588056 -1.434329"/>
    <point index="795" value=" 0.331374 1.046854 -1.442114"/>
    <point index="796" value=" 0.350424 0.815736 -1.492742"/>
    <point index="797" value=" 0.850475 0.815736 -1.179015"/>
    <point index="798" value=" 0.800602 1.046854 -1.147725"/>
    <point index="799" value=" -0.267674 0.809004 -1.492742"/>
    <point index="800" value=" -0.245694 0.588056 -1.434328"/>
    <point index="801" value=" -0.248624 1.046854 -1.442114"/>
    <point index="802" value=" -0.267674 0.815736 -1.492742"/>
    <point index="803" value=" -0.767725 0.809004 -1.179015"/>
    <point index="804" value=" -0.710182 0.588056 -1.142913"/>
    <point index="805" value=" -0.717851 1.046854 -1.147725"/>
    <point index="806" value=" -0.767725 0.815736 -1.179015"/>
    <point index="807" value=" -0.958727 0.809004 -0.671393"/>
    <point index="808" value=" -0.887601 0.588056 -0.671393"/>
    <point index="809" value=" -0.897080 1.046854 -0.671393"/>
    <point index="810" value=" -0.958727 0.815736 -0.671393"/>
    <point index="811" value=" -0.767725 0.809004 -0.163771"/>
    <point index="812" value=" -0.710182 0.588056 -0.199873"/>
    <point index="813" value=" -0.717851 1.046854 -0.195061"/>
    <point index="814" value=" -0.767725 0.815736 -0.163771"/>
    <point index="815" value=" -0.267673 0.809004 0.149957"/>
    <point index="816" value=" -0.245694 0.588056 0.091543"/>
    <point index="817" value=" -0.248623 1.046854 0.099328"/>
    <point index="818" value=" -0.267673 0.815736 0.149957"/>
    <point index="819" value=" 0.350424 0.809004 0.149957"/>
    <point index="820" value=" 0.328445 0.588056 0.091543"/>
    <point index="821" value=" 0.331374 1.046854 0.099328"/>
    <point index="822" value=" 0.350424 0.815736 0.149957"/>
    <point index="823" value=" 0.850475 0.809004 -0.163771"/>
    <point index="824" value=" 0.792933 0.588056 -0.199873"/>
    <point index="825" value=" 0.800602 1.046854 -0.195061"/>
    <point index="826" value=" 0.850475 0.815736 -0.163771"/>
    <point index="827" value=" 1.041478 0.809004 -0.671393"/>
    <point index="828" value=" 0.970351 0.588056 -0.671393"/>
    <point index="829" value=" 0.979831 1.046854 -0.671393"/>
    <point index="830" value=" 1.041478 0.815736 -0.671393"/>
    <point index="831" value=" 0.794957 2.410936 -1.144183"/>
    <point index="832" value=" 0.850475 2.634756 -1.179015"/>
    <point index="833" value=" 0.350424 2.634756 -1.492743"/>
    <point index="834" value=" 0.329218 2.410936 -1.436384"/>
    <point index="835" value=" 0.330684 2.870918 -1.440280"/>
    <point index="836" value=" 0.350424 2.642026 -1.492743"/>
    <point index="837" value=" 0.850475 2.642026 -1.179015"/>
    <point index="838" value=" 0.798795 2.870918 -1.146591"/>
    <point index="839" value=" -0.267674 2.634756 -1.492742"/>
    <point index="840" value=" -0.246467 2.410936 -1.436384"/>
    <point index="841" value=" -0.247933 2.870918 -1.440279"/>
    <point index="842" value=" -0.267674 2.642026 -1.492742"/>
    <point index="843" value=" -0.767725 2.634756 -1.179015"/>
    <point index="844" value=" -0.712207 2.410936 -1.144183"/>
    <point index="845" value=" -0.716044 2.870918 -1.146591"/>
    <point index="846" value=" -0.767725 2.642026 -1.179015"/>
    <point index="847" value=" -0.958727 2.634756 -0.671393"/>
    <point index="848" value=" -0.890103 2.410936 -0.671393"/>
    <point index="849" value=" -0.894847 2.870918 -0.671393"/>
    <point index="850" value=" -0.958727 2.642026 -0.671393"/>
    <point index="851" value=" -0.767725 2.634756 -0.163771"/>
    <point index="852" value=" -0.712206 2.410936 -0.198602"/>
    <point index="853" value=" -0.716044 2.870918 -0.196195"/>
    <point index="854" value=" -0.767725 2.642026 -0.163771"/>
    <point index="855" value=" -0.267673 2.634756 0.149957"/>
    <point index="856" value=" -0.246467 2.410936 0.093598"/>
    <point index="857" value=" -0.247933 2.870918 0.097494"/>
    <point index="858" value=" -0.267673 2.642026 0.149957"/>
    <point index="859" value=" 0.350424 2.634756 0.149957"/>
    <point index="860" value=" 0.329218 2.410936 0.093598"/>
    <point index="861" value=" 0.330684 2.870918 0.097494"/>
    <point index="862" value=" 0.350424 2.642026 0.149957"/>
    <point index="863" value=" 0.850475 2.634756 -0.163771"/>
    <point index="864" value=" 0.794957 2.410936 -0.198602"/>
    <point index="865" value=" 0.798795 2.870918 -0.196195"/>
    <point index="866" value=" 0.850475 2.642026 -0.163771"/>
    <point index="867" value=" 1.041478 2.634756 -0.671393"/>
    <point index="868" value=" 0.972853 2.410936 -0.671393"/>
    <point index="869" value=" 0.977597 2.870918 -0.671393"/>
    <point index="870" value=" 1.041478 2.642026 -0.671393"/>
  </shape>
  <weights deformer="skinCluster1" source="Neck2" shape="Neck_JointShape" layer="0" defaultValue="0.000" size="871" max="870">
    <point index="0" value="1.000"/>
    <point index="1" value="1.000"/>
    <point index="2" value="1.000"/>
    <point index="3" value="1.000"/>
    <point index="4" value="1.000"/>
    <point index="5" value="1.000"/>
    <point index="6" value="1.000"/>
    <point index="7" value="1.000"/>
    <point index="8" value="1.000"/>
    <point index="9" value="1.000"/>
    <point index="10" value="1.000"/>
    <point index="11" value="1.000"/>
    <point index="12" value="1.000"/>
    <point index="13" value="1.000"/>
    <point index="14" value="1.000"/>
    <point index="15" value="1.000"/>
    <point index="16" value="1.000"/>
    <point index="17" value="1.000"/>
    <point index="18" value="1.000"/>
    <point index="19" value="1.000"/>
    <point index="20" value="1.000"/>
    <point index="21" value="1.000"/>
    <point index="22" value="1.000"/>
    <point index="23" value="1.000"/>
    <point index="24" value="1.000"/>
    <point index="25" value="1.000"/>
    <point index="26" value="1.000"/>
    <point index="27" value="1.000"/>
    <point index="28" value="1.000"/>
    <point index="29" value="1.000"/>
    <point index="30" value="1.000"/>
    <point index="31" value="1.000"/>
    <point index="32" value="1.000"/>
    <point index="33" value="1.000"/>
    <point index="34" value="1.000"/>
    <point index="35" value="1.000"/>
    <point index="36" value="1.000"/>
    <point index="37" value="1.000"/>
    <point index="38" value="1.000"/>
    <point index="39" value="1.000"/>
    <point index="40" value="1.000"/>
    <point index="41" value="1.000"/>
    <point index="42" value="1.000"/>
    <point index="43" value="1.000"/>
    <point index="44" value="1.000"/>
    <point index="45" value="1.000"/>
    <point index="46" value="1.000"/>
    <point index="47" value="1.000"/>
    <point index="48" value="1.000"/>
    <point index="49" value="1.000"/>
    <point index="50" value="1.000"/>
    <point index="51" value="1.000"/>
    <point index="52" value="1.000"/>
    <point index="53" value="1.000"/>
    <point index="54" value="1.000"/>
    <point index="55" value="1.000"/>
    <point index="56" value="1.000"/>
    <point index="57" value="1.000"/>
    <point index="58" value="1.000"/>
    <point index="59" value="1.000"/>
    <point index="60" value="1.000"/>
    <point index="61" value="1.000"/>
    <point index="62" value="1.000"/>
    <point index="63" value="1.000"/>
    <point index="64" value="1.000"/>
    <point index="65" value="1.000"/>
    <point index="66" value="1.000"/>
    <point index="67" value="1.000"/>
    <point index="68" value="1.000"/>
    <point index="69" value="1.000"/>
    <point index="70" value="1.000"/>
    <point index="71" value="1.000"/>
    <point index="72" value="1.000"/>
    <point index="73" value="1.000"/>
    <point index="74" value="1.000"/>
    <point index="75" value="1.000"/>
    <point index="76" value="1.000"/>
    <point index="77" value="1.000"/>
    <point index="78" value="1.000"/>
    <point index="79" value="1.000"/>
    <point index="80" value="1.000"/>
    <point index="81" value="1.000"/>
    <point index="82" value="1.000"/>
    <point index="83" value="1.000"/>
    <point index="84" value="1.000"/>
    <point index="85" value="1.000"/>
    <point index="86" value="1.000"/>
    <point index="87" value="1.000"/>
    <point index="88" value="1.000"/>
    <point index="89" value="1.000"/>
    <point index="90" value="1.000"/>
    <point index="91" value="1.000"/>
    <point index="92" value="1.000"/>
    <point index="93" value="1.000"/>
    <point index="94" value="1.000"/>
    <point index="95" value="1.000"/>
    <point index="96" value="1.000"/>
    <point index="97" value="1.000"/>
    <point index="98" value="1.000"/>
    <point index="99" value="1.000"/>
    <point index="100" value="1.000"/>
    <point index="101" value="1.000"/>
    <point index="102" value="1.000"/>
    <point index="103" value="1.000"/>
    <point index="104" value="1.000"/>
    <point index="105" value="1.000"/>
    <point index="106" value="1.000"/>
    <point index="107" value="1.000"/>
    <point index="108" value="1.000"/>
    <point index="109" value="1.000"/>
    <point index="110" value="1.000"/>
    <point index="111" value="1.000"/>
    <point index="112" value="1.000"/>
    <point index="113" value="1.000"/>
    <point index="114" value="1.000"/>
    <point index="115" value="1.000"/>
    <point index="116" value="1.000"/>
    <point index="117" value="1.000"/>
    <point index="118" value="1.000"/>
    <point index="119" value="1.000"/>
    <point index="120" value="1.000"/>
    <point index="121" value="1.000"/>
    <point index="122" value="1.000"/>
    <point index="123" value="1.000"/>
    <point index="124" value="1.000"/>
    <point index="125" value="1.000"/>
    <point index="126" value="1.000"/>
    <point index="127" value="1.000"/>
    <point index="128" value="1.000"/>
    <point index="129" value="1.000"/>
    <point index="130" value="1.000"/>
    <point index="131" value="1.000"/>
    <point index="132" value="1.000"/>
    <point index="133" value="1.000"/>
    <point index="134" value="1.000"/>
    <point index="135" value="1.000"/>
    <point index="136" value="1.000"/>
    <point index="137" value="1.000"/>
    <point index="138" value="1.000"/>
    <point index="139" value="1.000"/>
    <point index="140" value="1.000"/>
    <point index="141" value="1.000"/>
    <point index="142" value="1.000"/>
    <point index="143" value="1.000"/>
    <point index="144" value="1.000"/>
    <point index="145" value="1.000"/>
    <point index="146" value="1.000"/>
    <point index="147" value="1.000"/>
    <point index="148" value="1.000"/>
    <point index="149" value="1.000"/>
    <point index="150" value="1.000"/>
    <point index="151" value="1.000"/>
    <point index="152" value="1.000"/>
    <point index="153" value="1.000"/>
    <point index="154" value="1.000"/>
    <point index="155" value="1.000"/>
    <point index="156" value="1.000"/>
    <point index="157" value="1.000"/>
    <point index="158" value="1.000"/>
    <point index="159" value="1.000"/>
    <point index="160" value="1.000"/>
    <point index="161" value="1.000"/>
    <point index="162" value="1.000"/>
    <point index="163" value="1.000"/>
    <point index="164" value="1.000"/>
    <point index="165" value="1.000"/>
    <point index="166" value="1.000"/>
    <point index="167" value="1.000"/>
    <point index="168" value="1.000"/>
    <point index="169" value="1.000"/>
    <point index="170" value="1.000"/>
    <point index="171" value="1.000"/>
    <point index="172" value="1.000"/>
    <point index="173" value="1.000"/>
    <point index="174" value="1.000"/>
    <point index="175" value="1.000"/>
    <point index="176" value="1.000"/>
    <point index="177" value="1.000"/>
    <point index="178" value="1.000"/>
    <point index="179" value="1.000"/>
    <point index="180" value="1.000"/>
    <point index="181" value="1.000"/>
    <point index="182" value="1.000"/>
    <point index="183" value="1.000"/>
    <point index="184" value="1.000"/>
    <point index="185" value="1.000"/>
    <point index="186" value="1.000"/>
    <point index="187" value="1.000"/>
    <point index="188" value="1.000"/>
    <point index="189" value="1.000"/>
    <point index="190" value="1.000"/>
    <point index="191" value="1.000"/>
    <point index="192" value="1.000"/>
    <point index="193" value="1.000"/>
    <point index="194" value="1.000"/>
    <point index="195" value="1.000"/>
    <point index="196" value="1.000"/>
    <point index="197" value="1.000"/>
    <point index="198" value="1.000"/>
    <point index="199" value="1.000"/>
    <point index="200" value="1.000"/>
    <point index="201" value="1.000"/>
    <point index="202" value="1.000"/>
    <point index="203" value="1.000"/>
    <point index="204" value="1.000"/>
    <point index="205" value="1.000"/>
    <point index="206" value="1.000"/>
    <point index="207" value="1.000"/>
    <point index="208" value="1.000"/>
    <point index="209" value="1.000"/>
    <point index="210" value="1.000"/>
    <point index="211" value="1.000"/>
    <point index="212" value="1.000"/>
    <point index="213" value="1.000"/>
    <point index="214" value="1.000"/>
    <point index="215" value="1.000"/>
    <point index="216" value="1.000"/>
    <point index="217" value="1.000"/>
    <point index="218" value="1.000"/>
    <point index="219" value="1.000"/>
    <point index="220" value="1.000"/>
    <point index="221" value="1.000"/>
    <point index="222" value="1.000"/>
    <point index="223" value="1.000"/>
    <point index="224" value="1.000"/>
    <point index="225" value="1.000"/>
    <point index="226" value="1.000"/>
    <point index="227" value="1.000"/>
    <point index="228" value="1.000"/>
    <point index="229" value="1.000"/>
    <point index="230" value="1.000"/>
    <point index="231" value="1.000"/>
    <point index="232" value="1.000"/>
    <point index="233" value="1.000"/>
    <point index="234" value="1.000"/>
    <point index="235" value="1.000"/>
    <point index="236" value="1.000"/>
    <point index="237" value="1.000"/>
    <point index="238" value="1.000"/>
    <point index="239" value="1.000"/>
    <point index="240" value="1.000"/>
    <point index="241" value="1.000"/>
    <point index="242" value="1.000"/>
    <point index="243" value="1.000"/>
    <point index="244" value="1.000"/>
    <point index="245" value="1.000"/>
    <point index="246" value="1.000"/>
    <point index="247" value="1.000"/>
    <point index="248" value="1.000"/>
    <point index="249" value="1.000"/>
    <point index="250" value="1.000"/>
    <point index="251" value="1.000"/>
    <point index="252" value="1.000"/>
    <point index="253" value="1.000"/>
    <point index="254" value="1.000"/>
    <point index="255" value="1.000"/>
    <point index="256" value="1.000"/>
    <point index="257" value="1.000"/>
    <point index="258" value="1.000"/>
    <point index="259" value="1.000"/>
    <point index="260" value="1.000"/>
    <point index="261" value="1.000"/>
    <point index="262" value="1.000"/>
    <point index="263" value="1.000"/>
    <point index="264" value="1.000"/>
    <point index="265" value="1.000"/>
    <point index="266" value="1.000"/>
    <point index="267" value="1.000"/>
    <point index="268" value="1.000"/>
    <point index="269" value="1.000"/>
    <point index="270" value="1.000"/>
    <point index="271" value="1.000"/>
    <point index="272" value="1.000"/>
    <point index="273" value="1.000"/>
    <point index="274" value="1.000"/>
    <point index="275" value="1.000"/>
    <point index="276" value="1.000"/>
    <point index="277" value="1.000"/>
    <point index="278" value="1.000"/>
    <point index="279" value="1.000"/>
    <point index="280" value="1.000"/>
    <point index="281" value="1.000"/>
    <point index="282" value="1.000"/>
    <point index="283" value="1.000"/>
    <point index="284" value="1.000"/>
    <point index="285" value="1.000"/>
    <point index="286" value="1.000"/>
    <point index="287" value="1.000"/>
    <point index="288" value="1.000"/>
    <point index="289" value="1.000"/>
    <point index="290" value="1.000"/>
    <point index="291" value="1.000"/>
    <point index="292" value="1.000"/>
    <point index="293" value="1.000"/>
    <point index="294" value="1.000"/>
    <point index="295" value="1.000"/>
    <point index="296" value="1.000"/>
    <point index="297" value="1.000"/>
    <point index="298" value="1.000"/>
    <point index="299" value="1.000"/>
    <point index="300" value="1.000"/>
    <point index="301" value="1.000"/>
    <point index="302" value="1.000"/>
    <point index="303" value="1.000"/>
    <point index="304" value="1.000"/>
    <point index="305" value="1.000"/>
    <point index="306" value="1.000"/>
    <point index="307" value="1.000"/>
    <point index="308" value="1.000"/>
    <point index="309" value="1.000"/>
    <point index="310" value="1.000"/>
    <point index="311" value="1.000"/>
    <point index="312" value="1.000"/>
    <point index="313" value="1.000"/>
    <point index="314" value="1.000"/>
    <point index="315" value="1.000"/>
    <point index="316" value="1.000"/>
    <point index="317" value="1.000"/>
    <point index="318" value="1.000"/>
    <point index="319" value="1.000"/>
    <point index="320" value="1.000"/>
    <point index="321" value="1.000"/>
    <point index="322" value="1.000"/>
    <point index="323" value="1.000"/>
    <point index="324" value="1.000"/>
    <point index="325" value="1.000"/>
    <point index="326" value="1.000"/>
    <point index="327" value="1.000"/>
    <point index="328" value="1.000"/>
    <point index="329" value="1.000"/>
    <point index="330" value="1.000"/>
    <point index="331" value="1.000"/>
    <point index="332" value="1.000"/>
    <point index="333" value="1.000"/>
    <point index="334" value="1.000"/>
    <point index="335" value="1.000"/>
    <point index="336" value="1.000"/>
    <point index="337" value="1.000"/>
    <point index="338" value="1.000"/>
    <point index="339" value="1.000"/>
    <point index="340" value="1.000"/>
    <point index="341" value="1.000"/>
    <point index="342" value="1.000"/>
    <point index="343" value="1.000"/>
    <point index="344" value="1.000"/>
    <point index="345" value="1.000"/>
    <point index="346" value="1.000"/>
    <point index="347" value="1.000"/>
    <point index="348" value="1.000"/>
    <point index="349" value="1.000"/>
    <point index="350" value="1.000"/>
    <point index="351" value="1.000"/>
    <point index="352" value="1.000"/>
    <point index="353" value="1.000"/>
    <point index="354" value="1.000"/>
    <point index="355" value="1.000"/>
    <point index="356" value="1.000"/>
    <point index="357" value="1.000"/>
    <point index="358" value="1.000"/>
    <point index="359" value="1.000"/>
    <point index="360" value="1.000"/>
    <point index="361" value="1.000"/>
    <point index="362" value="1.000"/>
    <point index="363" value="1.000"/>
    <point index="364" value="1.000"/>
    <point index="365" value="1.000"/>
    <point index="366" value="1.000"/>
    <point index="367" value="1.000"/>
    <point index="368" value="1.000"/>
    <point index="369" value="1.000"/>
    <point index="370" value="1.000"/>
    <point index="371" value="1.000"/>
    <point index="372" value="1.000"/>
    <point index="373" value="1.000"/>
    <point index="374" value="1.000"/>
    <point index="375" value="1.000"/>
    <point index="376" value="1.000"/>
    <point index="377" value="1.000"/>
    <point index="378" value="1.000"/>
    <point index="379" value="1.000"/>
    <point index="380" value="1.000"/>
    <point index="381" value="1.000"/>
    <point index="382" value="1.000"/>
    <point index="383" value="1.000"/>
    <point index="384" value="1.000"/>
    <point index="385" value="1.000"/>
    <point index="386" value="1.000"/>
    <point index="387" value="1.000"/>
    <point index="388" value="1.000"/>
    <point index="389" value="1.000"/>
    <point index="390" value="1.000"/>
    <point index="391" value="1.000"/>
    <point index="392" value="1.000"/>
    <point index="393" value="1.000"/>
    <point index="394" value="1.000"/>
    <point index="395" value="1.000"/>
    <point index="396" value="1.000"/>
    <point index="397" value="1.000"/>
    <point index="398" value="1.000"/>
    <point index="399" value="1.000"/>
    <point index="400" value="1.000"/>
    <point index="401" value="1.000"/>
    <point index="402" value="1.000"/>
    <point index="403" value="1.000"/>
    <point index="404" value="1.000"/>
    <point index="405" value="1.000"/>
    <point index="406" value="1.000"/>
    <point index="407" value="1.000"/>
    <point index="408" value="1.000"/>
    <point index="409" value="1.000"/>
    <point index="410" value="1.000"/>
    <point index="411" value="1.000"/>
    <point index="412" value="1.000"/>
    <point index="413" value="1.000"/>
    <point index="414" value="1.000"/>
    <point index="415" value="1.000"/>
    <point index="416" value="1.000"/>
    <point index="417" value="1.000"/>
    <point index="418" value="1.000"/>
    <point index="419" value="1.000"/>
    <point index="420" value="1.000"/>
    <point index="421" value="1.000"/>
    <point index="422" value="1.000"/>
    <point index="423" value="1.000"/>
    <point index="424" value="1.000"/>
    <point index="425" value="1.000"/>
    <point index="426" value="1.000"/>
    <point index="427" value="1.000"/>
    <point index="428" value="1.000"/>
    <point index="429" value="1.000"/>
    <point index="430" value="1.000"/>
    <point index="431" value="1.000"/>
    <point index="432" value="1.000"/>
    <point index="433" value="1.000"/>
    <point index="434" value="1.000"/>
    <point index="435" value="1.000"/>
    <point index="436" value="1.000"/>
    <point index="437" value="1.000"/>
    <point index="438" value="1.000"/>
    <point index="439" value="1.000"/>
    <point index="440" value="1.000"/>
    <point index="441" value="1.000"/>
    <point index="442" value="1.000"/>
    <point index="443" value="1.000"/>
    <point index="444" value="1.000"/>
    <point index="445" value="1.000"/>
    <point index="446" value="1.000"/>
    <point index="447" value="1.000"/>
    <point index="448" value="1.000"/>
    <point index="449" value="1.000"/>
    <point index="450" value="1.000"/>
    <point index="451" value="1.000"/>
    <point index="452" value="1.000"/>
    <point index="453" value="1.000"/>
    <point index="454" value="1.000"/>
    <point index="455" value="1.000"/>
    <point index="456" value="1.000"/>
    <point index="457" value="1.000"/>
    <point index="458" value="1.000"/>
    <point index="459" value="1.000"/>
    <point index="460" value="1.000"/>
    <point index="461" value="1.000"/>
    <point index="462" value="1.000"/>
    <point index="463" value="1.000"/>
    <point index="464" value="1.000"/>
    <point index="465" value="1.000"/>
    <point index="466" value="1.000"/>
    <point index="467" value="1.000"/>
    <point index="468" value="1.000"/>
    <point index="469" value="1.000"/>
    <point index="470" value="1.000"/>
    <point index="471" value="1.000"/>
    <point index="472" value="1.000"/>
    <point index="473" value="1.000"/>
    <point index="474" value="1.000"/>
    <point index="475" value="1.000"/>
    <point index="476" value="1.000"/>
    <point index="477" value="1.000"/>
    <point index="478" value="1.000"/>
    <point index="479" value="1.000"/>
    <point index="480" value="1.000"/>
    <point index="481" value="1.000"/>
    <point index="482" value="1.000"/>
    <point index="483" value="1.000"/>
    <point index="484" value="1.000"/>
    <point index="485" value="1.000"/>
    <point index="486" value="1.000"/>
    <point index="487" value="1.000"/>
    <point index="488" value="1.000"/>
    <point index="489" value="1.000"/>
    <point index="490" value="1.000"/>
    <point index="491" value="1.000"/>
    <point index="492" value="1.000"/>
    <point index="493" value="1.000"/>
    <point index="494" value="1.000"/>
    <point index="495" value="1.000"/>
    <point index="496" value="1.000"/>
    <point index="497" value="1.000"/>
    <point index="498" value="1.000"/>
    <point index="499" value="1.000"/>
    <point index="500" value="1.000"/>
    <point index="501" value="1.000"/>
    <point index="502" value="1.000"/>
    <point index="503" value="1.000"/>
    <point index="504" value="1.000"/>
    <point index="505" value="1.000"/>
    <point index="506" value="1.000"/>
    <point index="507" value="1.000"/>
    <point index="508" value="1.000"/>
    <point index="509" value="1.000"/>
    <point index="510" value="1.000"/>
    <point index="511" value="1.000"/>
    <point index="512" value="1.000"/>
    <point index="513" value="1.000"/>
    <point index="514" value="1.000"/>
    <point index="515" value="1.000"/>
    <point index="516" value="1.000"/>
    <point index="517" value="1.000"/>
    <point index="518" value="1.000"/>
    <point index="519" value="1.000"/>
    <point index="520" value="1.000"/>
    <point index="521" value="1.000"/>
    <point index="522" value="1.000"/>
    <point index="523" value="1.000"/>
    <point index="524" value="1.000"/>
    <point index="525" value="1.000"/>
    <point index="526" value="1.000"/>
    <point index="527" value="1.000"/>
    <point index="528" value="1.000"/>
    <point index="529" value="1.000"/>
    <point index="530" value="1.000"/>
    <point index="531" value="1.000"/>
    <point index="532" value="1.000"/>
    <point index="533" value="1.000"/>
    <point index="534" value="1.000"/>
    <point index="535" value="1.000"/>
    <point index="536" value="1.000"/>
    <point index="537" value="1.000"/>
    <point index="538" value="1.000"/>
    <point index="539" value="1.000"/>
    <point index="540" value="1.000"/>
    <point index="541" value="1.000"/>
    <point index="542" value="1.000"/>
    <point index="543" value="1.000"/>
    <point index="544" value="1.000"/>
    <point index="545" value="1.000"/>
    <point index="546" value="1.000"/>
    <point index="547" value="1.000"/>
    <point index="548" value="1.000"/>
    <point index="549" value="1.000"/>
    <point index="550" value="1.000"/>
    <point index="551" value="1.000"/>
    <point index="552" value="1.000"/>
    <point index="553" value="1.000"/>
    <point index="554" value="1.000"/>
    <point index="555" value="1.000"/>
    <point index="556" value="1.000"/>
    <point index="557" value="1.000"/>
    <point index="558" value="1.000"/>
    <point index="559" value="1.000"/>
    <point index="560" value="1.000"/>
    <point index="561" value="1.000"/>
    <point index="562" value="1.000"/>
    <point index="563" value="1.000"/>
    <point index="564" value="1.000"/>
    <point index="565" value="1.000"/>
    <point index="566" value="1.000"/>
    <point index="567" value="1.000"/>
    <point index="568" value="1.000"/>
    <point index="569" value="1.000"/>
    <point index="570" value="1.000"/>
    <point index="571" value="1.000"/>
    <point index="572" value="1.000"/>
    <point index="573" value="1.000"/>
    <point index="574" value="1.000"/>
    <point index="575" value="1.000"/>
    <point index="576" value="1.000"/>
    <point index="577" value="1.000"/>
    <point index="578" value="1.000"/>
    <point index="579" value="1.000"/>
    <point index="580" value="1.000"/>
    <point index="581" value="1.000"/>
    <point index="582" value="1.000"/>
    <point index="583" value="1.000"/>
    <point index="584" value="1.000"/>
    <point index="585" value="1.000"/>
    <point index="586" value="1.000"/>
    <point index="587" value="1.000"/>
    <point index="588" value="1.000"/>
    <point index="589" value="1.000"/>
    <point index="590" value="1.000"/>
    <point index="591" value="1.000"/>
    <point index="592" value="1.000"/>
    <point index="593" value="1.000"/>
    <point index="594" value="1.000"/>
    <point index="595" value="1.000"/>
    <point index="596" value="1.000"/>
    <point index="597" value="1.000"/>
    <point index="598" value="1.000"/>
    <point index="599" value="1.000"/>
    <point index="600" value="1.000"/>
    <point index="601" value="1.000"/>
    <point index="602" value="1.000"/>
    <point index="603" value="1.000"/>
    <point index="604" value="1.000"/>
    <point index="605" value="1.000"/>
    <point index="606" value="1.000"/>
    <point index="607" value="1.000"/>
    <point index="608" value="1.000"/>
    <point index="609" value="1.000"/>
    <point index="610" value="1.000"/>
    <point index="611" value="1.000"/>
    <point index="612" value="1.000"/>
    <point index="613" value="1.000"/>
    <point index="614" value="1.000"/>
    <point index="615" value="1.000"/>
    <point index="616" value="1.000"/>
    <point index="617" value="1.000"/>
    <point index="618" value="1.000"/>
    <point index="619" value="1.000"/>
    <point index="620" value="1.000"/>
    <point index="621" value="1.000"/>
    <point index="622" value="1.000"/>
    <point index="623" value="1.000"/>
    <point index="624" value="1.000"/>
    <point index="625" value="1.000"/>
    <point index="626" value="1.000"/>
    <point index="627" value="1.000"/>
    <point index="628" value="1.000"/>
    <point index="629" value="1.000"/>
    <point index="630" value="1.000"/>
    <point index="631" value="1.000"/>
    <point index="632" value="1.000"/>
    <point index="633" value="1.000"/>
    <point index="634" value="1.000"/>
    <point index="635" value="1.000"/>
    <point index="636" value="1.000"/>
    <point index="637" value="1.000"/>
    <point index="638" value="1.000"/>
    <point index="639" value="1.000"/>
    <point index="640" value="1.000"/>
    <point index="641" value="1.000"/>
    <point index="642" value="1.000"/>
    <point index="643" value="1.000"/>
    <point index="644" value="1.000"/>
    <point index="645" value="1.000"/>
    <point index="646" value="1.000"/>
    <point index="647" value="1.000"/>
    <point index="648" value="1.000"/>
    <point index="649" value="1.000"/>
    <point index="650" value="1.000"/>
    <point index="651" value="1.000"/>
    <point index="652" value="1.000"/>
    <point index="653" value="1.000"/>
    <point index="654" value="1.000"/>
    <point index="655" value="1.000"/>
    <point index="656" value="1.000"/>
    <point index="657" value="1.000"/>
    <point index="658" value="1.000"/>
    <point index="659" value="1.000"/>
    <point index="660" value="1.000"/>
    <point index="661" value="1.000"/>
    <point index="662" value="1.000"/>
    <point index="663" value="1.000"/>
    <point index="664" value="1.000"/>
    <point index="665" value="1.000"/>
    <point index="666" value="1.000"/>
    <point index="667" value="1.000"/>
    <point index="668" value="1.000"/>
    <point index="669" value="1.000"/>
    <point index="670" value="1.000"/>
    <point index="671" value="1.000"/>
    <point index="672" value="1.000"/>
    <point index="673" value="1.000"/>
    <point index="674" value="1.000"/>
    <point index="675" value="1.000"/>
    <point index="676" value="1.000"/>
    <point index="677" value="1.000"/>
    <point index="678" value="1.000"/>
    <point index="679" value="1.000"/>
    <point index="680" value="1.000"/>
    <point index="681" value="1.000"/>
    <point index="682" value="1.000"/>
    <point index="683" value="1.000"/>
    <point index="684" value="1.000"/>
    <point index="685" value="1.000"/>
    <point index="686" value="1.000"/>
    <point index="687" value="1.000"/>
    <point index="688" value="1.000"/>
    <point index="689" value="1.000"/>
    <point index="690" value="1.000"/>
    <point index="691" value="1.000"/>
    <point index="692" value="1.000"/>
    <point index="693" value="1.000"/>
    <point index="694" value="1.000"/>
    <point index="695" value="1.000"/>
    <point index="696" value="1.000"/>
    <point index="697" value="1.000"/>
    <point index="698" value="1.000"/>
    <point index="699" value="1.000"/>
    <point index="700" value="1.000"/>
    <point index="701" value="1.000"/>
    <point index="702" value="1.000"/>
    <point index="703" value="1.000"/>
    <point index="704" value="1.000"/>
    <point index="705" value="1.000"/>
    <point index="706" value="1.000"/>
    <point index="707" value="1.000"/>
    <point index="708" value="1.000"/>
    <point index="709" value="1.000"/>
    <point index="710" value="1.000"/>
    <point index="711" value="1.000"/>
    <point index="712" value="1.000"/>
    <point index="713" value="1.000"/>
    <point index="714" value="1.000"/>
    <point index="715" value="1.000"/>
    <point index="716" value="1.000"/>
    <point index="717" value="1.000"/>
    <point index="718" value="1.000"/>
    <point index="719" value="1.000"/>
    <point index="720" value="1.000"/>
    <point index="721" value="1.000"/>
    <point index="722" value="1.000"/>
    <point index="723" value="1.000"/>
    <point index="724" value="1.000"/>
    <point index="725" value="1.000"/>
    <point index="726" value="1.000"/>
    <point index="727" value="1.000"/>
    <point index="728" value="1.000"/>
    <point index="729" value="1.000"/>
    <point index="730" value="1.000"/>
    <point index="731" value="1.000"/>
    <point index="732" value="1.000"/>
    <point index="733" value="1.000"/>
    <point index="734" value="1.000"/>
    <point index="735" value="1.000"/>
    <point index="736" value="1.000"/>
    <point index="737" value="1.000"/>
    <point index="738" value="1.000"/>
    <point index="739" value="1.000"/>
    <point index="740" value="1.000"/>
    <point index="741" value="1.000"/>
    <point index="742" value="1.000"/>
    <point index="743" value="1.000"/>
    <point index="744" value="1.000"/>
    <point index="745" value="1.000"/>
    <point index="746" value="1.000"/>
    <point index="747" value="1.000"/>
    <point index="748" value="1.000"/>
    <point index="749" value="1.000"/>
    <point index="750" value="1.000"/>
    <point index="751" value="1.000"/>
    <point index="752" value="1.000"/>
    <point index="753" value="1.000"/>
    <point index="754" value="1.000"/>
    <point index="755" value="1.000"/>
    <point index="756" value="1.000"/>
    <point index="757" value="1.000"/>
    <point index="758" value="1.000"/>
    <point index="759" value="1.000"/>
    <point index="760" value="1.000"/>
    <point index="761" value="1.000"/>
    <point index="762" value="1.000"/>
    <point index="763" value="1.000"/>
    <point index="764" value="1.000"/>
    <point index="765" value="1.000"/>
    <point index="766" value="1.000"/>
    <point index="767" value="1.000"/>
    <point index="768" value="1.000"/>
    <point index="769" value="1.000"/>
    <point index="770" value="1.000"/>
    <point index="771" value="1.000"/>
    <point index="772" value="1.000"/>
    <point index="773" value="1.000"/>
    <point index="774" value="1.000"/>
    <point index="775" value="1.000"/>
    <point index="776" value="1.000"/>
    <point index="777" value="1.000"/>
    <point index="778" value="1.000"/>
    <point index="779" value="1.000"/>
    <point index="780" value="1.000"/>
    <point index="781" value="1.000"/>
    <point index="782" value="1.000"/>
    <point index="783" value="1.000"/>
    <point index="784" value="1.000"/>
    <point index="785" value="1.000"/>
    <point index="786" value="1.000"/>
    <point index="787" value="1.000"/>
    <point index="788" value="1.000"/>
    <point index="789" value="1.000"/>
    <point index="790" value="1.000"/>
    <point index="791" value="1.000"/>
    <point index="792" value="1.000"/>
    <point index="793" value="1.000"/>
    <point index="794" value="1.000"/>
    <point index="795" value="1.000"/>
    <point index="796" value="1.000"/>
    <point index="797" value="1.000"/>
    <point index="798" value="1.000"/>
    <point index="799" value="1.000"/>
    <point index="800" value="1.000"/>
    <point index="801" value="1.000"/>
    <point index="802" value="1.000"/>
    <point index="803" value="1.000"/>
    <point index="804" value="1.000"/>
    <point index="805" value="1.000"/>
    <point index="806" value="1.000"/>
    <point index="807" value="1.000"/>
    <point index="808" value="1.000"/>
    <point index="809" value="1.000"/>
    <point index="810" value="1.000"/>
    <point index="811" value="1.000"/>
    <point index="812" value="1.000"/>
    <point index="813" value="1.000"/>
    <point index="814" value="1.000"/>
    <point index="815" value="1.000"/>
    <point index="816" value="1.000"/>
    <point index="817" value="1.000"/>
    <point index="818" value="1.000"/>
    <point index="819" value="1.000"/>
    <point index="820" value="1.000"/>
    <point index="821" value="1.000"/>
    <point index="822" value="1.000"/>
    <point index="823" value="1.000"/>
    <point index="824" value="1.000"/>
    <point index="825" value="1.000"/>
    <point index="826" value="1.000"/>
    <point index="827" value="1.000"/>
    <point index="828" value="1.000"/>
    <point index="829" value="1.000"/>
    <point index="830" value="1.000"/>
    <point index="831" value="1.000"/>
    <point index="832" value="1.000"/>
    <point index="833" value="1.000"/>
    <point index="834" value="1.000"/>
    <point index="835" value="1.000"/>
    <point index="836" value="1.000"/>
    <point index="837" value="1.000"/>
    <point index="838" value="1.000"/>
    <point index="839" value="1.000"/>
    <point index="840" value="1.000"/>
    <point index="841" value="1.000"/>
    <point index="842" value="1.000"/>
    <point index="843" value="1.000"/>
    <point index="844" value="1.000"/>
    <point index="845" value="1.000"/>
    <point index="846" value="1.000"/>
    <point index="847" value="1.000"/>
    <point index="848" value="1.000"/>
    <point index="849" value="1.000"/>
    <point index="850" value="1.000"/>
    <point index="851" value="1.000"/>
    <point index="852" value="1.000"/>
    <point index="853" value="1.000"/>
    <point index="854" value="1.000"/>
    <point index="855" value="1.000"/>
    <point index="856" value="1.000"/>
    <point index="857" value="1.000"/>
    <point index="858" value="1.000"/>
    <point index="859" value="1.000"/>
    <point index="860" value="1.000"/>
    <point index="861" value="1.000"/>
    <point index="862" value="1.000"/>
    <point index="863" value="1.000"/>
    <point index="864" value="1.000"/>
    <point index="865" value="1.000"/>
    <point index="866" value="1.000"/>
    <point index="867" value="1.000"/>
    <point index="868" value="1.000"/>
    <point index="869" value="1.000"/>
    <point index="870" value="1.000"/>
  </weights>
  <weights deformer="skinCluster1" source="Bend1" shape="Neck_JointShape" layer="1" defaultValue="0.000" size="0" max="0"/>
  <weights deformer="skinCluster1" source="Bend2" shape="Neck_JointShape" layer="2" defaultValue="0.000" size="0" max="0"/>
  <weights deformer="skinCluster1" source="Mid_head" shape="Neck_JointShape" layer="3" defaultValue="0.000" size="0" max="0"/>
  <weights deformer="skinCluster1" source="Bottom_Head" shape="Neck_JointShape" layer="4" defaultValue="0.000" size="0" max="0"/>
  <weights deformer="skinCluster1" source="Top_Head" shape="Neck_JointShape" layer="5" defaultValue="0.000" size="0" max="0"/>
</deformerWeight>
